MANIFEST.in
README.rst
setup.py
gearbox/__init__.py
gearbox/command.py
gearbox/commandmanager.py
gearbox/main.py
gearbox/template.py
gearbox.egg-info/PKG-INFO
gearbox.egg-info/SOURCES.txt
gearbox.egg-info/dependency_links.txt
gearbox.egg-info/entry_points.txt
gearbox.egg-info/not-zip-safe
gearbox.egg-info/requires.txt
gearbox.egg-info/top_level.txt
gearbox/commands/__init__.py
gearbox/commands/help.py
gearbox/commands/patch.py
gearbox/commands/scaffold.py
gearbox/commands/serve.py
gearbox/commands/setup_app.py
gearbox/commands/basic_package/__init__.py
gearbox/commands/basic_package/command.py
gearbox/commands/basic_package/template/MANIFEST.in_tmpl
gearbox/commands/basic_package/template/README.rst_tmpl
gearbox/commands/basic_package/template/setup.cfg_tmpl
gearbox/commands/basic_package/template/setup.py_tmpl
gearbox/commands/basic_package/template/+package+/__init__.py
gearbox/utils/__init__.py
gearbox/utils/copydir.py
gearbox/utils/log.py
gearbox/utils/plugins.py