Metadata-Version: 1.1
Name: gearbox
Version: 0.2.1
Summary: Command line toolkit born as a PasteScript replacement for the TurboGears2 web framework
Home-page: https://github.com/TurboGears/gearbox
Author: Alessandro Molina
Author-email: amol@turbogears.org
License: MIT
Keywords: web framework command-line setup
Platform: UNKNOWN
Classifier: Intended Audience :: Developers
Classifier: License :: OSI Approved :: MIT License
Classifier: Framework :: TurboGears
Classifier: Programming Language :: Python
Classifier: Programming Language :: Python :: 2.6
Classifier: Programming Language :: Python :: 2.7
Classifier: Programming Language :: Python :: 3
Classifier: Programming Language :: Python :: 3.2
Classifier: Programming Language :: Python :: 3.3
Classifier: Programming Language :: Python :: 3.4
Classifier: Programming Language :: Python :: 3.5
Classifier: Programming Language :: Python :: 3.6
Classifier: Programming Language :: Python :: 3.7
Classifier: Topic :: Internet :: WWW/HTTP :: WSGI
Classifier: Topic :: Software Development :: Libraries :: Python Modules
